{
  "sheet": "bosses2.png",
  "size": {
    "w": 1122,
    "h": 1402
  },
  "bosses": {
    "vesper": {
      "down": {
        "idle": [
          {
            "x": 665,
            "y": 90,
            "w": 132,
            "h": 105
          },
          {
            "x": 816,
            "y": 90,
            "w": 116,
            "h": 105
          },
          {
            "x": 947,
            "y": 90,
            "w": 123,
            "h": 105
          }
        ],
        "moveL": [
          {
            "x": 662,
            "y": 210,
            "w": 135,
            "h": 105
          },
          {
            "x": 805,
            "y": 210,
            "w": 131,
            "h": 105
          },
          {
            "x": 939,
            "y": 210,
            "w": 135,
            "h": 105
          }
        ],
        "moveR": [
          {
            "x": 662,
            "y": 322,
            "w": 135,
            "h": 105
          },
          {
            "x": 800,
            "y": 322,
            "w": 136,
            "h": 105
          },
          {
            "x": 939,
            "y": 322,
            "w": 104,
            "h": 105
          }
        ],
        "hit": [
          {
            "x": 662,
            "y": 436,
            "w": 135,
            "h": 105
          }
        ],
        "attack": [
          {
            "x": 662,
            "y": 548,
            "w": 135,
            "h": 105
          }
        ]
      },
      "up": {
        "idle": [
          {
            "x": 662,
            "y": 688,
            "w": 118,
            "h": 105
          },
          {
            "x": 800,
            "y": 688,
            "w": 128,
            "h": 105
          },
          {
            "x": 950,
            "y": 688,
            "w": 124,
            "h": 105
          }
        ],
        "moveL": [
          {
            "x": 662,
            "y": 799,
            "w": 135,
            "h": 105
          },
          {
            "x": 810,
            "y": 799,
            "w": 126,
            "h": 105
          },
          {
            "x": 939,
            "y": 799,
            "w": 135,
            "h": 105
          }
        ],
        "moveR": [
          {
            "x": 662,
            "y": 903,
            "w": 130,
            "h": 105
          },
          {
            "x": 800,
            "y": 903,
            "w": 133,
            "h": 105
          },
          {
            "x": 943,
            "y": 903,
            "w": 130,
            "h": 105
          }
        ],
        "hit": [
          {
            "x": 662,
            "y": 1011,
            "w": 135,
            "h": 105
          }
        ],
        "attack": [
          {
            "x": 662,
            "y": 1123,
            "w": 135,
            "h": 105
          }
        ]
      }
    }
  }
}